{"diff_netsenders_30": 9, "diff_netsenders_365": 51, "diff_netsenders_7": 5, "diff_netsent_30": 34, "diff_netsent_365": 285, "diff_netsent_7": 15, "first_date": "2015-06-11", "last_date": "2015-11-09", "percentage_senders_30": 64, "percentage_senders_365": 0, "percentage_senders_7": 166, "percentage_sent_30": 121, "percentage_sent_365": 0, "percentage_sent_7": 500, "repositories": 1, "senders": 51, "senders_30": 23, "senders_365": 51, "senders_7": 8, "senders_init": 29, "senders_response": 47, "sent": 285, "sent_30": 62, "sent_365": 285, "sent_7": 18, "sent_response": 214, "threads": 71}