{"changed": 630, "changed_30": 157, "changed_365": 630, "changed_7": 47, "changers": 54, "changers_30": 25, "changers_365": 54, "changers_7": 12, "closed": 134, "closed_30": 3, "closed_365": 134, "closed_7": 0, "closers": 18, "closers_30": 2, "closers_365": 18, "closers_7": 0, "diff_netchanged_30": -373, "diff_netchanged_365": 630, "diff_netchanged_7": 18, "diff_netchangers_30": 3, "diff_netchangers_365": 54, "diff_netchangers_7": 0, "diff_netclosed_30": -89, "diff_netclosed_365": 134, "diff_netclosed_7": 0, "diff_netclosers_30": -4, "diff_netclosers_365": 18, "diff_netclosers_7": 0, "diff_netopened_30": -30, "diff_netopened_365": 646, "diff_netopened_7": 8, "diff_netopeners_30": 2, "diff_netopeners_365": 55, "diff_netopeners_7": -3, "opened": 646, "opened_30": 111, "opened_365": 646, "opened_7": 25, "openers": 55, "openers_30": 23, "openers_365": 55, "openers_7": 7, "percentage_changed_30": 70, "percentage_changed_365": 0, "percentage_changed_7": 62, "percentage_changers_30": 13, "percentage_changers_365": 0, "percentage_changers_7": 0, "percentage_closed_30": 96, "percentage_closed_365": 0, "percentage_closed_7": 0, "percentage_closers_30": 66, "percentage_closers_365": 0, "percentage_closers_7": 0, "percentage_opened_30": 21, "percentage_opened_365": 0, "percentage_opened_7": 47, "percentage_openers_30": 9, "percentage_openers_365": 0, "percentage_openers_7": 30, "trackers": 1}