{"diff_netsenders_30": -15, "diff_netsenders_365": 63, "diff_netsenders_7": 3, "diff_netsent_30": -57, "diff_netsent_365": 877, "diff_netsent_7": 12, "first_date": "2015-06-11", "last_date": "2016-07-11", "percentage_senders_30": 62, "percentage_senders_365": 262, "percentage_senders_7": 0, "percentage_sent_30": 72, "percentage_sent_365": 2192, "percentage_sent_7": 0, "repositories": 1, "senders": 91, "senders_30": 9, "senders_365": 87, "senders_7": 3, "senders_init": 60, "senders_response": 75, "sent": 925, "sent_30": 22, "sent_365": 917, "sent_7": 12, "sent_response": 716, "threads": 209}