{"abandoned": [0, 0, 0, 0, 0, 0, 0, 0, 0], "active_core_reviewers": [0, 0, 0, 1, 7, 12, 8, 18, 8], "closed": [0, 0, 0, 0, 0, 0, 0, 0, 0], "date": ["Mar 2015", "Apr 2015", "May 2015", "Jun 2015", "Jul 2015", "Aug 2015", "Sep 2015", "Oct 2015", "Nov 2015"], "id": [0, 1, 2, 3, 4, 5, 6, 7, 8], "merged": [0, 0, 0, 0, 0, 0, 0, 0, 0], "month": [24183, 24184, 24185, 24186, 24187, 24188, 24189, 24190, 24191], "new": [0, 0, 0, 0, 0, 0, 0, 0, 0], "opened": [0, 0, 0, 0, 0, 0, 0, 0, 0], "participants": [1, 0, 0, 1, 4, 14, 33, 114, 334], "patchset_submitters": [1, 3, 2, 4, 9, 10, 8, 12, 12], "pending": [2, 4, 4, 15, 54, 50, 46, 84, 66], "review_time_days_avg": [0, 0, 0, 0, 0, 0, 0, 0, 0], "review_time_days_median": [0, 0, 0, 0, 0, 0, 0, 0, 0], "reviewers": [6, 4, 8, 17, 24, 29, 29, 39, 28], "sent_patchsets": [7, 18, 26, 56, 264, 335, 267, 455, 496], "submitted": [2, 4, 4, 15, 54, 50, 46, 84, 66], "submitters": [1, 2, 1, 4, 10, 10, 9, 12, 11], "unixtime": ["1425168000", "1427846400", "1430438400", "1433116800", "1435708800", "1438387200", "1441065600", "1443657600", "1446336000"], "voted_patchsets": [6, 16, 26, 67, 246, 320, 261, 375, 351]}