{"actions": 20967, "added_lines": 3217105.0, "added_lines_30": 101780.0, "added_lines_365": 3217105.0, "added_lines_7": 7902.0, "authors": 49, "authors_30": 17, "authors_365": 49, "authors_7": 12, "avg_commits_author": 30.39, "avg_commits_month": 165.44, "avg_files_author": 304.35, "avg_files_month": 1657.0, "branches": 61, "commits": 1489, "commits_30": 149, "commits_365": 1489, "commits_7": 48, "committers": 45, "diff_netadded_lines_30": 19602.0, "diff_netadded_lines_365": 3217105.0, "diff_netadded_lines_7": -66691.0, "diff_netauthors_30": -3, "diff_netauthors_365": 49, "diff_netauthors_7": 6, "diff_netcommits_30": -46, "diff_netcommits_365": 1489, "diff_netcommits_7": 17, "diff_netfiles_30": -217, "diff_netfiles_365": 14913, "diff_netfiles_7": -384, "diff_netnewauthors_30": 0, "diff_netnewauthors_365": 48, "diff_netnewauthors_7": 0, "diff_netremoved_lines_30": 34995.0, "diff_netremoved_lines_365": 442575.0, "diff_netremoved_lines_7": -33303.0, "files": 14913, "files_30": 909, "files_365": 14913, "files_7": 115, "first_date": "2015-03-09", "last_date": "2016-01-08", "newauthors": 48, "newauthors_30": 1, "newauthors_365": 48, "newauthors_7": 0, "percentage_added_lines_30": 23, "percentage_added_lines_365": 0, "percentage_added_lines_7": 89, "percentage_authors_30": 15, "percentage_authors_365": 0, "percentage_authors_7": 100, "percentage_commits_30": 23, "percentage_commits_365": 0, "percentage_commits_7": 54, "percentage_files_30": 19, "percentage_files_365": 0, "percentage_files_7": 76, "percentage_newauthors_30": 0, "percentage_newauthors_365": 0, "percentage_newauthors_7": 0, "percentage_removed_lines_30": 80, "percentage_removed_lines_365": 0, "percentage_removed_lines_7": 78, "removed_lines": 442575.0, "removed_lines_30": 78422.0, "removed_lines_365": 442575.0, "removed_lines_7": 9287.0, "repositories": 1}