{"actions": 10495, "added_lines": 1144424.0, "added_lines_30": 15605.0, "added_lines_365": 1001184.0, "added_lines_7": 8513.0, "authors": 39, "authors_30": 1, "authors_365": 1, "authors_7": 1, "avg_commits_author": 24.46, "avg_commits_month": 119.25, "avg_files_author": 193.69, "avg_files_month": 944.25, "branches": 45, "commits": 954, "commits_30": 48, "commits_365": 231, "commits_7": 6, "committers": 43, "diff_netadded_lines_30": -386.0, "diff_netadded_lines_365": 1001184.0, "diff_netadded_lines_7": -6656.0, "diff_netauthors_30": 0, "diff_netauthors_365": 1, "diff_netauthors_7": 0, "diff_netcommits_30": 11, "diff_netcommits_365": 231, "diff_netcommits_7": -3, "diff_netfiles_30": -501, "diff_netfiles_365": 5153, "diff_netfiles_7": -11, "diff_netnewauthors_30": -4, "diff_netnewauthors_365": 38, "diff_netnewauthors_7": -1, "diff_netremoved_lines_30": -630.0, "diff_netremoved_lines_365": 151407.0, "diff_netremoved_lines_7": 12573.0, "files": 7554, "files_30": 162, "files_365": 5153, "files_7": 108, "first_date": "2015-12-04", "last_date": "2015-12-14", "newauthors": 38, "newauthors_30": 1, "newauthors_365": 38, "newauthors_7": 0, "percentage_added_lines_30": 2, "percentage_added_lines_365": 0, "percentage_added_lines_7": 43, "percentage_authors_30": 0, "percentage_authors_365": 0, "percentage_authors_7": 0, "percentage_commits_30": 29, "percentage_commits_365": 0, "percentage_commits_7": 33, "percentage_files_30": 75, "percentage_files_365": 0, "percentage_files_7": 9, "percentage_newauthors_30": 80, "percentage_newauthors_365": 0, "percentage_newauthors_7": 100, "percentage_removed_lines_30": 4, "percentage_removed_lines_365": 0, "percentage_removed_lines_7": 1741, "removed_lines": 320986.0, "removed_lines_30": 13380.0, "removed_lines_365": 151407.0, "removed_lines_7": 13295.0, "repositories": 1}