{"diff_netsenders_30": -2, "diff_netsenders_365": 91, "diff_netsenders_7": 3, "diff_netsent_30": 75, "diff_netsent_365": 3428, "diff_netsent_7": 35, "first_date": "2015-04-29", "last_date": "2016-02-22", "percentage_senders_30": 5, "percentage_senders_365": 0, "percentage_senders_7": 12, "percentage_sent_30": 14, "percentage_sent_365": 0, "percentage_sent_7": 31, "repositories": 2, "senders": 91, "senders_30": 38, "senders_365": 91, "senders_7": 27, "senders_init": 54, "senders_response": 88, "sent": 3428, "sent_30": 605, "sent_365": 3428, "sent_7": 146, "sent_response": 2727, "threads": 701}