{"actions": [78269, 56095, 14283, 1], "added_lines": [8274627.0, 6000225.0, 324039.0, 25.0], "added_lines_30": [61093.0, 32681.0, 28878.0, 0], "added_lines_365": [5237718.0, 4073918.0, 324038.0, 25.0], "added_lines_7": [3040.0, 442.0, 18.0, 0], "authors": [59, 20, 2, 1], "authors_30": [24, 8, 2, 0], "authors_365": [48, 18, 2, 1], "authors_7": [11, 2, 1, 0], "avg_commits_author": [56.2, 80.25, 256.5, 1.0], "avg_commits_month": [221.07, 107.0, 42.75, null], "avg_files_author": [812.27, 1883.15, 4853.5, 1.0], "avg_files_month": [3194.93, 2510.87, 808.92, null], "branches": [157, 111, 53, 1], "commits": [3316, 1605, 513, 1], "commits_30": [257, 82, 42, 0], "commits_365": [2811, 1339, 512, 1], "commits_7": [33, 4, 2, 0], "committers": [52, 18, 2, 0], "diff_netadded_lines_30": [-875822.0, -844574.0, -1045.0, 0], "diff_netadded_lines_365": [2200809.0, 2147611.0, 324037.0, 25.0], "diff_netadded_lines_7": [-3717.0, -111.0, -19.0, 0], "diff_netauthors_30": [4, 2, 0, 0], "diff_netauthors_365": [24, 8, 1, 1], "diff_netauthors_7": [-2, -1, 0, 0], "diff_netcommits_30": [-162, -75, -32, 0], "diff_netcommits_365": [2306, 1073, 511, 1], "diff_netcommits_7": [-26, -4, 1, 0], "diff_netfiles_30": [-6031, -3843, -1725, 0], "diff_netfiles_365": [26223, 22108, 9705, 1], "diff_netfiles_7": [-37, 2, 1, 0], "diff_netnewauthors_30": [1, 0, 0, 0], "diff_netnewauthors_365": [12, 1, 0, 1], "diff_netnewauthors_7": [0, 0, 0, 0], "diff_netremoved_lines_30": [-25581.0, -7968.0, -6931.0, 0], "diff_netremoved_lines_365": [3658502.0, 2696528.0, 289213.0, 1.0], "diff_netremoved_lines_7": [-2992.0, -69.0, 22.0, 0], "files": [47924, 37663, 9707, 1], "files_30": [2292, 1362, 1206, 0], "files_365": [38189, 30051, 9706, 1], "files_7": [125, 23, 5, 0], "first_date": ["2015-03-09", "2015-03-11", "2015-06-16", "2015-07-28"], "last_date": ["2016-07-05", "2016-07-05", "2016-07-03", "2015-07-28"], "name": ["Pivotal", "The Apache Software Foundation", "VMWare", "IBM"], "newauthors": [58, 19, 2, 1], "newauthors_30": [2, 0, 0, 0], "newauthors_365": [35, 10, 1, 1], "newauthors_7": [0, 0, 0, 0], "percentage_added_lines_30": [93, 96, 3, 0], "percentage_added_lines_365": [72, 111, 32403700, 0], "percentage_added_lines_7": [55, 20, 51, 0], "percentage_authors_30": [20, 33, 0, 0], "percentage_authors_365": [100, 80, 100, 0], "percentage_authors_7": [15, 33, 0, 0], "percentage_commits_30": [38, 47, 43, 0], "percentage_commits_365": [456, 403, 51100, 0], "percentage_commits_7": [44, 50, 100, 0], "percentage_files_30": [72, 73, 58, 0], "percentage_files_365": [219, 278, 970500, 0], "percentage_files_7": [22, 9, 25, 0], "percentage_newauthors_30": [100, 0, 0, 0], "percentage_newauthors_365": [52, 11, 0, 0], "percentage_newauthors_7": [0, 0, 0, 0], "percentage_removed_lines_30": [29, 23, 22, 0], "percentage_removed_lines_365": [11146, 16276, 28921300, 0], "percentage_removed_lines_7": [57, 11, 146, 0], "removed_lines": [3724148.0, 2729662.0, 289215.0, 1.0], "removed_lines_30": [61896.0, 26177.0, 23363.0, 0], "removed_lines_365": [3691325.0, 2713095.0, 289214.0, 1.0], "removed_lines_7": [2192.0, 558.0, 37.0, 0], "repositories": [1, 1, 1, 1]}