{"actions": 83297, "added_lines": 8373257.0, "added_lines_30": 61297, "added_lines_365": 5334647, "added_lines_7": 2681, "authors": 80, "authors_30": 25, "authors_365": 60, "authors_7": 14, "avg_commits_author": 42.35, "avg_commits_month": 225.87, "avg_files_author": 652.3, "avg_files_month": 3478.93, "branches": 157, "commits": 3388, "commits_30": 264, "commits_365": 2851, "commits_7": 37, "committers": 80, "core": 15, "diff_netadded_lines_30": -876028, "diff_netadded_lines_365": 2296037, "diff_netadded_lines_7": -4746, "diff_netauthors_30": 5, "diff_netauthors_365": 27, "diff_netauthors_7": 3, "diff_netcommits_30": -159, "diff_netcommits_365": 2314, "diff_netcommits_7": -20, "diff_netfiles_30": -6149, "diff_netfiles_365": 30586, "diff_netfiles_7": -51, "diff_netnewauthors_30": 2, "diff_netnewauthors_365": 15, "diff_netnewauthors_7": 0, "diff_netremoved_lines_30": -31849, "diff_netremoved_lines_365": 3701265, "diff_netremoved_lines_7": -3538, "domains": 23, "files": 52184, "files_30": 2207, "files_365": 42558, "files_7": 120, "first_date": "2015-03-09", "last_date": "2016-07-06", "newauthors": 79, "newauthors_30": 3, "newauthors_365": 47, "newauthors_7": 0, "occasional": 49, "organizations": 4, "percentage_added_lines_30": 93, "percentage_added_lines_365": 75, "percentage_added_lines_7": 63, "percentage_authors_30": 25, "percentage_authors_365": 81, "percentage_authors_7": 27, "percentage_commits_30": 37, "percentage_commits_365": 430, "percentage_commits_7": 35, "percentage_files_30": 73, "percentage_files_365": 255, "percentage_files_7": 29, "percentage_newauthors_30": 200, "percentage_newauthors_365": 46, "percentage_newauthors_7": 0, "percentage_removed_lines_30": 35, "percentage_removed_lines_365": 11256, "percentage_removed_lines_7": 64, "regular": 16, "removed_lines": 3767027.0, "removed_lines_30": 59017, "removed_lines_365": 3734146, "removed_lines_7": 1966, "repositories": 1, "type": "git", "url": "https://github.com/apache/incubator-geode.git"}