{"actions": [83200], "added_lines": [8371500.0], "added_lines_30": [59950.0], "added_lines_365": [5826014.0], "added_lines_7": [4518.0], "authors": [80], "authors_30": [25], "authors_365": [60], "authors_7": [12], "avg_commits_author": [41.99], "avg_commits_month": [223.93], "avg_files_author": [651.5], "avg_files_month": [3474.67], "branches": [156], "commits": [3359], "commits_30": [239], "commits_365": [2833], "commits_7": [48], "committers": [80], "diff_netadded_lines_30": [-926149.0], "diff_netadded_lines_365": [3280528.0], "diff_netadded_lines_7": [-2438.0], "diff_netauthors_30": [5], "diff_netauthors_365": [27], "diff_netauthors_7": [-5], "diff_netcommits_30": [-209], "diff_netcommits_365": [2307], "diff_netcommits_7": [-15], "diff_netfiles_30": [-6735], "diff_netfiles_365": [33689], "diff_netfiles_7": [-50], "diff_netnewauthors_30": [2], "diff_netnewauthors_365": [15], "diff_netnewauthors_7": [0], "diff_netremoved_lines_30": [-74860.0], "diff_netremoved_lines_365": [3699680.0], "diff_netremoved_lines_7": [-3537.0], "files": [52120], "files_30": [2253], "files_365": [43678], "files_7": [153], "first_date": ["2015-03-09"], "last_date": ["2016-07-03"], "name": ["incubator-geode.git"], "newauthors": [79], "newauthors_30": [3], "newauthors_365": [47], "newauthors_7": [0], "percentage_added_lines_30": [93], "percentage_added_lines_365": [128], "percentage_added_lines_7": [35], "percentage_authors_30": [25], "percentage_authors_365": [81], "percentage_authors_7": [29], "percentage_commits_30": [46], "percentage_commits_365": [438], "percentage_commits_7": [23], "percentage_files_30": [74], "percentage_files_365": [337], "percentage_files_7": [24], "percentage_newauthors_30": [200], "percentage_newauthors_365": [46], "percentage_newauthors_7": [0], "percentage_removed_lines_30": [55], "percentage_removed_lines_365": [11289], "percentage_removed_lines_7": [58], "removed_lines": [3765220.0], "removed_lines_30": [60599.0], "removed_lines_365": [3732450.0], "removed_lines_7": [2477.0], "repositories": [1]}