{"actions": 26004, "added_lines": 3316015.0, "added_lines_30": 98043, "added_lines_365": 3316015, "added_lines_7": 981, "authors": 68, "authors_30": 15, "authors_365": 68, "authors_7": 2, "avg_commits_author": 23.18, "avg_commits_month": 157.6, "avg_files_author": 281.88, "avg_files_month": 1916.8, "branches": 63, "commits": 1576, "commits_30": 139, "commits_365": 1576, "commits_7": 25, "committers": 68, "core": 12, "diff_netadded_lines_30": 11869, "diff_netadded_lines_365": 3316015, "diff_netadded_lines_7": -6921, "diff_netauthors_30": -9, "diff_netauthors_365": 68, "diff_netauthors_7": -10, "diff_netcommits_30": -62, "diff_netcommits_365": 1576, "diff_netcommits_7": -23, "diff_netfiles_30": -248, "diff_netfiles_365": 19168, "diff_netfiles_7": -92, "diff_netnewauthors_30": -6, "diff_netnewauthors_365": 67, "diff_netnewauthors_7": 0, "diff_netremoved_lines_30": 10995, "diff_netremoved_lines_365": 485321, "diff_netremoved_lines_7": -8695, "domains": 21, "files": 19168, "files_30": 788, "files_365": 19168, "files_7": 23, "first_date": "2015-03-09", "last_date": "2016-01-16", "newauthors": 67, "newauthors_30": 0, "newauthors_365": 67, "newauthors_7": 0, "occasional": 36, "organizations": 4, "percentage_added_lines_30": 13, "percentage_added_lines_365": 0, "percentage_added_lines_7": 87, "percentage_authors_30": 37, "percentage_authors_365": 0, "percentage_authors_7": 83, "percentage_commits_30": 30, "percentage_commits_365": 0, "percentage_commits_7": 47, "percentage_files_30": 23, "percentage_files_365": 0, "percentage_files_7": 80, "percentage_newauthors_30": 100, "percentage_newauthors_365": 0, "percentage_newauthors_7": 0, "percentage_removed_lines_30": 20, "percentage_removed_lines_365": 0, "percentage_removed_lines_7": 93, "regular": 20, "removed_lines": 485321.0, "removed_lines_30": 65477, "removed_lines_365": 485321, "removed_lines_7": 592, "repositories": 1, "type": "git", "url": "https://github.com/apache/incubator-geode.git"}