{"actions": [68222], "added_lines": [7300484.0], "added_lines_30": [803244.0], "added_lines_365": [6218783.0], "added_lines_7": [393612.0], "authors": [76], "authors_30": [24], "authors_365": [61], "authors_7": [10], "avg_commits_author": [34.2], "avg_commits_month": [199.92], "avg_files_author": [565.75], "avg_files_month": [3307.46], "branches": [117], "commits": [2599], "commits_30": [278], "commits_365": [2119], "commits_7": [48], "committers": [76], "diff_netadded_lines_30": [37304.0], "diff_netadded_lines_365": [5137082.0], "diff_netadded_lines_7": [26536.0], "diff_netauthors_30": [3], "diff_netauthors_365": [35], "diff_netauthors_7": [-4], "diff_netcommits_30": [-36], "diff_netcommits_365": [1639], "diff_netcommits_7": [-8], "diff_netfiles_30": [-4401], "diff_netfiles_365": [36532], "diff_netfiles_7": [-342], "diff_netnewauthors_30": [0], "diff_netnewauthors_365": [25], "diff_netnewauthors_7": [0], "diff_netremoved_lines_30": [25774.0], "diff_netremoved_lines_365": [3543784.0], "diff_netremoved_lines_7": [-353267.0], "files": [42997], "files_30": [4841], "files_365": [40485], "files_7": [1624], "first_date": ["2015-03-09"], "last_date": ["2016-04-29"], "name": ["incubator-geode.git"], "newauthors": [75], "newauthors_30": [1], "newauthors_365": [50], "newauthors_7": [0], "percentage_added_lines_30": [4], "percentage_added_lines_365": [474], "percentage_added_lines_7": [7], "percentage_authors_30": [14], "percentage_authors_365": [134], "percentage_authors_7": [28], "percentage_commits_30": [11], "percentage_commits_365": [341], "percentage_commits_7": [14], "percentage_files_30": [47], "percentage_files_365": [924], "percentage_files_7": [17], "percentage_newauthors_30": [0], "percentage_newauthors_365": [100], "percentage_newauthors_7": [0], "percentage_removed_lines_30": [5], "percentage_removed_lines_365": [101891], "percentage_removed_lines_7": [96], "removed_lines": [3550740.0], "removed_lines_30": [462212.0], "removed_lines_365": [3547262.0], "removed_lines_7": [12051.0], "repositories": [1]}