{"actions": 25373, "added_lines": 4209128.0, "added_lines_30": 61359.0, "added_lines_365": 4209128.0, "added_lines_7": 4604.0, "authors": 17, "authors_30": 6, "authors_365": 17, "authors_7": 4, "avg_commits_author": 58.24, "avg_commits_month": 90.0, "avg_files_author": 1224.71, "avg_files_month": 1892.73, "branches": 62, "commits": 990, "commits_30": 104, "commits_365": 990, "commits_7": 16, "committers": 16, "diff_netadded_lines_30": -1915255.0, "diff_netadded_lines_365": 4209128.0, "diff_netadded_lines_7": -2984.0, "diff_netauthors_30": -1, "diff_netauthors_365": 17, "diff_netauthors_7": -1, "diff_netcommits_30": -31, "diff_netcommits_365": 990, "diff_netcommits_7": -6, "diff_netfiles_30": -7889, "diff_netfiles_365": 20820, "diff_netfiles_7": -67, "diff_netnewauthors_30": 0, "diff_netnewauthors_365": 16, "diff_netnewauthors_7": 0, "diff_netremoved_lines_30": -1827072.0, "diff_netremoved_lines_365": 2108308.0, "diff_netremoved_lines_7": -2140.0, "files": 20820, "files_30": 1501, "files_365": 20820, "files_7": 118, "first_date": "2015-03-11", "last_date": "2016-03-08", "newauthors": 16, "newauthors_30": 0, "newauthors_365": 16, "newauthors_7": 0, "percentage_added_lines_30": 96, "percentage_added_lines_365": 0, "percentage_added_lines_7": 39, "percentage_authors_30": 14, "percentage_authors_365": 0, "percentage_authors_7": 19, "percentage_commits_30": 22, "percentage_commits_365": 0, "percentage_commits_7": 27, "percentage_files_30": 84, "percentage_files_365": 0, "percentage_files_7": 36, "percentage_newauthors_30": 0, "percentage_newauthors_365": 0, "percentage_newauthors_7": 0, "percentage_removed_lines_30": 96, "percentage_removed_lines_365": 0, "percentage_removed_lines_7": 48, "removed_lines": 2108308.0, "removed_lines_30": 59829.0, "removed_lines_365": 2108308.0, "removed_lines_7": 2291.0, "repositories": 1}