{"diff_netsenders_30": -2, "diff_netsenders_365": 24, "diff_netsenders_7": 0, "diff_netsent_30": -72, "diff_netsent_365": 2777, "diff_netsent_7": 89, "first_date": "2015-04-28", "last_date": "2016-03-21", "percentage_senders_30": 12, "percentage_senders_365": 0, "percentage_senders_7": 0, "percentage_sent_30": 16, "percentage_sent_365": 0, "percentage_sent_7": 136, "repositories": 2, "senders": 24, "senders_30": 14, "senders_365": 24, "senders_7": 12, "senders_init": 23, "senders_response": 21, "sent": 2777, "sent_30": 375, "sent_365": 2777, "sent_7": 154, "sent_response": 2164, "threads": 613}