{"actions": 37719, "added_lines": 5958344.0, "added_lines_30": 876306.0, "added_lines_365": 4879032.0, "added_lines_7": 7741.0, "authors": 18, "authors_30": 5, "authors_365": 17, "authors_7": 4, "avg_commits_author": 80.28, "avg_commits_month": 103.21, "avg_files_author": 1681.72, "avg_files_month": 2162.21, "branches": 92, "commits": 1445, "commits_30": 150, "commits_365": 1194, "commits_7": 24, "committers": 16, "diff_netadded_lines_30": 761542.0, "diff_netadded_lines_365": 3799720.0, "diff_netadded_lines_7": 5532.0, "diff_netauthors_30": -1, "diff_netauthors_365": 10, "diff_netauthors_7": -1, "diff_netcommits_30": 23, "diff_netcommits_365": 943, "diff_netcommits_7": 8, "diff_netfiles_30": 2798, "diff_netfiles_365": 22617, "diff_netfiles_7": 438, "diff_netnewauthors_30": 0, "diff_netnewauthors_365": 5, "diff_netnewauthors_7": 0, "diff_netremoved_lines_30": -84247.0, "diff_netremoved_lines_365": 2673545.0, "diff_netremoved_lines_7": 11031.0, "files": 30271, "files_30": 5173, "files_365": 26601, "files_7": 536, "first_date": "2015-03-11", "last_date": "2016-06-07", "newauthors": 17, "newauthors_30": 0, "newauthors_365": 11, "newauthors_7": 0, "percentage_added_lines_30": 663, "percentage_added_lines_365": 352, "percentage_added_lines_7": 250, "percentage_authors_30": 16, "percentage_authors_365": 142, "percentage_authors_7": 19, "percentage_commits_30": 18, "percentage_commits_365": 375, "percentage_commits_7": 50, "percentage_files_30": 117, "percentage_files_365": 567, "percentage_files_7": 446, "percentage_newauthors_30": 0, "percentage_newauthors_365": 83, "percentage_newauthors_7": 0, "percentage_removed_lines_30": 71, "percentage_removed_lines_365": 89296, "percentage_removed_lines_7": 691, "removed_lines": 2679533.0, "removed_lines_30": 33585.0, "removed_lines_365": 2676539.0, "removed_lines_7": 12626.0, "repositories": 1}