{"actions": 6549, "added_lines": 141037.0, "added_lines_30": 23156.0, "added_lines_365": 141037.0, "added_lines_7": 9516.0, "authors": 2, "authors_30": 2, "authors_365": 2, "authors_7": 2, "avg_commits_author": 129.0, "avg_commits_month": 32.25, "avg_files_author": 2170.0, "avg_files_month": 542.5, "branches": 29, "commits": 258, "commits_30": 59, "commits_365": 258, "commits_7": 21, "committers": 2, "diff_netadded_lines_30": -44435.0, "diff_netadded_lines_365": 141037.0, "diff_netadded_lines_7": 4836.0, "diff_netauthors_30": 0, "diff_netauthors_365": 2, "diff_netauthors_7": 0, "diff_netcommits_30": 5, "diff_netcommits_365": 258, "diff_netcommits_7": 4, "diff_netfiles_30": -2430, "diff_netfiles_365": 4340, "diff_netfiles_7": 381, "diff_netnewauthors_30": 0, "diff_netnewauthors_365": 2, "diff_netnewauthors_7": 0, "diff_netremoved_lines_30": -39497.0, "diff_netremoved_lines_365": 111286.0, "diff_netremoved_lines_7": 7341.0, "files": 4340, "files_30": 723, "files_365": 4340, "files_7": 488, "first_date": "2015-06-16", "last_date": "2016-03-15", "newauthors": 2, "newauthors_30": 0, "newauthors_365": 2, "newauthors_7": 0, "percentage_added_lines_30": 65, "percentage_added_lines_365": 0, "percentage_added_lines_7": 103, "percentage_authors_30": 0, "percentage_authors_365": 0, "percentage_authors_7": 0, "percentage_commits_30": 9, "percentage_commits_365": 0, "percentage_commits_7": 23, "percentage_files_30": 77, "percentage_files_365": 0, "percentage_files_7": 356, "percentage_newauthors_30": 0, "percentage_newauthors_365": 0, "percentage_newauthors_7": 0, "percentage_removed_lines_30": 67, "percentage_removed_lines_365": 0, "percentage_removed_lines_7": 372, "removed_lines": 111286.0, "removed_lines_30": 18666.0, "removed_lines_365": 111286.0, "removed_lines_7": 9314.0, "repositories": 1}